chgnet/__init__.py
chgnet/py.typed
chgnet/data/__init__.py
chgnet/data/dataset.py
chgnet/graph/__init__.py
chgnet/graph/converter.py
chgnet/graph/crystalgraph.py
chgnet/graph/cygraph.cp311-win_amd64.pyd
chgnet/graph/cygraph.pyx
chgnet/graph/graph.py
chgnet/graph/fast_converter_libraries/create_graph.c
chgnet/graph/fast_converter_libraries/uthash.h
chgnet/model/__init__.py
chgnet/model/basis.py
chgnet/model/composition_model.py
chgnet/model/dynamics.py
chgnet/model/encoders.py
chgnet/model/functions.py
chgnet/model/layers.py
chgnet/model/model.py
chgnet/pretrained/0.2.0/README.md
chgnet/pretrained/0.2.0/chgnet_0.2.0_e30f77s348m32.pth.tar
chgnet/pretrained/0.3.0/README.md
chgnet/pretrained/0.3.0/chgnet_0.3.0_e29f68s314m37.pth.tar
chgnet/pretrained/r2scan/README.md
chgnet/pretrained/r2scan/chgnet_r2scan_transfer_learning_e15f36s161m23.pth.tar
chgnet/trainer/__init__.py
chgnet/trainer/trainer.py
chgnet/utils/__init__.py
chgnet/utils/common_utils.py
chgnet/utils/vasp_utils.py
chgnet-0.4.2.dist-info/licenses/LICENSE
chgnet-0.4.2.dist-info/METADATA
chgnet-0.4.2.dist-info/WHEEL
chgnet-0.4.2.dist-info/top_level.txt
chgnet-0.4.2.dist-info/RECORD
