Metadata-Version: 2.4
Name: chgnet
Version: 0.4.2
Summary: Pretrained Universal Neural Network Potential for Charge-informed Atomistic Modeling
Author-email: Bowen Deng <bowendeng@berkeley.edu>
License: Modified BSD
Project-URL: Source, https://github.com/CederGroupHub/chgnet
Project-URL: Package, https://pypi.org/project/chgnet
Classifier: Intended Audience :: Science/Research
Classifier: License :: OSI Approved :: BSD License
Classifier: Operating System :: OS Independent
Classifier: Programming Language :: Python :: 3.10
Classifier: Programming Language :: Python :: 3.11
Classifier: Programming Language :: Python :: 3.12
Classifier: Topic :: Scientific/Engineering :: Artificial Intelligence
Classifier: Topic :: Scientific/Engineering :: Chemistry
Classifier: Topic :: Scientific/Engineering :: Physics
Requires-Python: >=3.10
License-File: LICENSE
Requires-Dist: ase>=3.23.0
Requires-Dist: cython>=3
Requires-Dist: numpy>=1.26
Requires-Dist: nvidia-ml-py3>=7.352.0
Requires-Dist: pymatgen>=2024.9.10
Requires-Dist: torch>=2.4.1
Requires-Dist: typing-extensions>=4.12
Provides-Extra: test
Requires-Dist: pytest-cov>=4; extra == "test"
Requires-Dist: pytest>=8; extra == "test"
Requires-Dist: wandb>=0.17; extra == "test"
Provides-Extra: examples
Requires-Dist: crystal-toolkit>=2023.11.3; extra == "examples"
Requires-Dist: pandas>=2.2; extra == "examples"
Provides-Extra: docs
Requires-Dist: lazydocs>=0.4; extra == "docs"
Provides-Extra: logging
Requires-Dist: wandb>=0.17.2; extra == "logging"
Provides-Extra: dispersion
Requires-Dist: dftd4>=3.6; extra == "dispersion"
Requires-Dist: torch-dftd>=0.4; extra == "dispersion"
Dynamic: license-file
